[{"__symbolic":"module","version":4,"metadata":{"SohoIconsComponent":{"__symbolic":"class","decorators":[{"__symbolic":"call","expression":{"__symbolic":"reference","module":"@angular/core","name":"Component","line":6,"character":1},"arguments":[{"selector":"soho-icons","templateUrl":"svg.html"}]}],"members":{"none":[{"__symbolic":"property","decorators":[{"__symbolic":"call","expression":{"__symbolic":"reference","module":"@angular/core","name":"HostBinding","line":11,"character":3},"arguments":["style.display"]}]}]}}}}]