[{"__symbolic":"module","version":4,"metadata":{"SohoFormCompactComponent":{"__symbolic":"class","decorators":[{"__symbolic":"call","expression":{"__symbolic":"reference","module":"@angular/core","name":"Component","line":13,"character":1},"arguments":[{"selector":"[soho-form-compact]","template":"<ng-content></ng-content>","changeDetection":{"__symbolic":"select","expression":{"__symbolic":"reference","module":"@angular/core","name":"ChangeDetectionStrategy","line":16,"character":19},"member":"OnPush"}}]}],"members":{"isFormCompact":[{"__symbolic":"property","decorators":[{"__symbolic":"call","expression":{"__symbolic":"reference","module":"@angular/core","name":"HostBinding","line":23,"character":3},"arguments":["class.form-compact"]}]}],"__ctor__":[{"__symbolic":"constructor","parameters":[{"__symbolic":"reference","module":"@angular/core","name":"ElementRef","line":32,"character":21},{"__symbolic":"reference","module":"@angular/core","name":"NgZone","line":33,"character":20}]}],"ngAfterViewInit":[{"__symbolic":"method"}],"ngAfterViewChecked":[{"__symbolic":"method"}],"ngOnDestroy":[{"__symbolic":"method"}]}}}}]